vid_split/__init__.py
vid_split/__main__.py
vid_split/__version__.py
vid_split/helpers/ParallelFFmpeg.py
vid_split/helpers/__init__.py
vid_split/helpers/cover_utils.py
vid_split/helpers/ffprobe.py
vid_split/helpers/ffprogress.py
vid_split/split/SegmentData.py
vid_split/split/SilenceFinder.py
vid_split/split/Splitter.py
vid_split/split/__init__.py
vid_split/split/subcommand.py
vid_split-0.3.0.dist-info/METADATA
vid_split-0.3.0.dist-info/WHEEL
vid_split-0.3.0.dist-info/entry_points.txt
vid_split-0.3.0.dist-info/top_level.txt
vid_split-0.3.0.dist-info/RECORD
